handybits/__init__.py
handybits/__version__.py
handybits/converters.py
handybits/datetime.py
handybits/di_container.py
handybits/enum.py
handybits/event_loop.py
handybits/exceptions.py
handybits/http.py
handybits/ids.py
handybits/iterated.py
handybits/logger.py
handybits/multilang.py
handybits/retry.py
handybits/singleton.py
handybits/strings.py
handybits/urls.py
handybits-0.1.0.dist-info/METADATA
handybits-0.1.0.dist-info/WHEEL
handybits-0.1.0.dist-info/top_level.txt
handybits-0.1.0.dist-info/RECORD
