Metadata-Version: 2.4
Name: handybits
Version: 0.1.0
Summary: Python utils kit for any cases.
Author-email: V-ampire <webjob010@gmail.com>
License: MIT
Project-URL: Homepage, https://github.com/V-ampire/handybits
Requires-Python: >=3.12
Requires-Dist: aiohttp>=3.12.15
Requires-Dist: python-dateutil>=2.9.0.post0
Requires-Dist: tenacity>=9.1.2
Requires-Dist: tldextract>=5.3.0
Provides-Extra: dev
Requires-Dist: build; extra == "dev"
Requires-Dist: twine; extra == "dev"
